Metadata-Version: 2.1
Name: demoMath01
Version: 0.0.0
Summary: demo add and subtract functions
Home-page: UNKNOWN
Author: Sanyam Gupta
Author-email: sanyam233@gmail.com
License: UNKNOWN
Platform: UNKNOWN
Classifier: Programming Language :: Python :: 3
Classifier: License :: OSI Approved :: MIT License
Classifier: Operating System :: OS Independent
